odoo8_addon_l10n_es_aeat_mod303-8.0.3.4.0-py3.8-nspkg.pth
odoo_addons/l10n_es_aeat_mod303/README.rst
odoo_addons/l10n_es_aeat_mod303/__init__.py
odoo_addons/l10n_es_aeat_mod303/__openerp__.py
odoo_addons/l10n_es_aeat_mod303/data/aeat_export_mod303_2017_data.xml
odoo_addons/l10n_es_aeat_mod303/data/aeat_export_mod303_2018_data.xml
odoo_addons/l10n_es_aeat_mod303/data/aeat_export_mod303_2021_data.xml
odoo_addons/l10n_es_aeat_mod303/data/aeat_export_mod303_data.xml
odoo_addons/l10n_es_aeat_mod303/data/l10n_es_aeat_mod303_report_activity_code_data.xml
odoo_addons/l10n_es_aeat_mod303/data/tax_code_map_mod303_data.xml
odoo_addons/l10n_es_aeat_mod303/data/202107/aeat.mod.map.tax.code.csv
odoo_addons/l10n_es_aeat_mod303/data/202107/aeat.mod.map.tax.code.line.csv
odoo_addons/l10n_es_aeat_mod303/data/202107/aeat.model.export.config.csv
odoo_addons/l10n_es_aeat_mod303/data/202107/aeat.model.export.config.line.csv
odoo_addons/l10n_es_aeat_mod303/data/2022/aeat.model.export.config.csv
odoo_addons/l10n_es_aeat_mod303/data/2022/aeat.model.export.config.line.csv
odoo_addons/l10n_es_aeat_mod303/docs/DR303e21v100.xlsx
odoo_addons/l10n_es_aeat_mod303/docs/DR303e21v200.xlsx
odoo_addons/l10n_es_aeat_mod303/docs/DR303e22.xlsx
odoo_addons/l10n_es_aeat_mod303/i18n/bg.po
odoo_addons/l10n_es_aeat_mod303/i18n/ca.po
odoo_addons/l10n_es_aeat_mod303/i18n/ca_ES.po
odoo_addons/l10n_es_aeat_mod303/i18n/cs.po
odoo_addons/l10n_es_aeat_mod303/i18n/en_US.po
odoo_addons/l10n_es_aeat_mod303/i18n/es.po
odoo_addons/l10n_es_aeat_mod303/i18n/es_CO.po
odoo_addons/l10n_es_aeat_mod303/i18n/es_CR.po
odoo_addons/l10n_es_aeat_mod303/i18n/eu.po
odoo_addons/l10n_es_aeat_mod303/i18n/fr.po
odoo_addons/l10n_es_aeat_mod303/i18n/gl.po
odoo_addons/l10n_es_aeat_mod303/i18n/hr.po
odoo_addons/l10n_es_aeat_mod303/i18n/l10n_es_aeat_mod303.pot
odoo_addons/l10n_es_aeat_mod303/i18n/nl.po
odoo_addons/l10n_es_aeat_mod303/i18n/pl.po
odoo_addons/l10n_es_aeat_mod303/i18n/pt.po
odoo_addons/l10n_es_aeat_mod303/i18n/pt_BR.po
odoo8_addon_l10n_es_aeat_mod303-8.0.3.4.0.dist-info/METADATA
odoo8_addon_l10n_es_aeat_mod303-8.0.3.4.0.dist-info/WHEEL
odoo8_addon_l10n_es_aeat_mod303-8.0.3.4.0.dist-info/namespace_packages.txt
odoo8_addon_l10n_es_aeat_mod303-8.0.3.4.0.dist-info/top_level.txt
odoo8_addon_l10n_es_aeat_mod303-8.0.3.4.0.dist-info/RECORD
