Metadata-Version: 2.1
Name: odoo8-addon-l10n-es-aeat-mod303
Version: 8.0.3.4.0
Summary: AEAT modelo 303
Home-page: https://github.com/OCA/l10n-spain
Author: Guadaltech,AvanzOSC,Serv. Tecnol. Avanzados - Pedro M. Baeza,Antiun Ingeniería S.L.,Comunitea,Odoo Community Association (OCA),Otherway Creatives S.L.
Author-email: support@odoo-community.org
License: AGPL-3
Platform: UNKNOWN
Classifier: Programming Language :: Python
Classifier: Framework :: Odoo
Classifier: Framework :: Odoo :: 8.0
Classifier: License :: OSI Approved :: GNU Affero General Public License v3
Requires-Python: ~=2.7
Requires-Dist: odoo8-addon-l10n-es-aeat
Requires-Dist: odoo (<9.0a,>=8.0a)
